intervals/__init__.py
intervals/basic_interval.py
intervals/datetime_interval.py
intervals/float_interval.py
scikit_intervals-0.1.2.dist-info/DESCRIPTION.rst
scikit_intervals-0.1.2.dist-info/METADATA
scikit_intervals-0.1.2.dist-info/RECORD
scikit_intervals-0.1.2.dist-info/WHEEL
scikit_intervals-0.1.2.dist-info/metadata.json
scikit_intervals-0.1.2.dist-info/top_level.txt
skintervals/__init__.py
skintervals/basic_interval.py
skintervals/datetime_interval.py
skintervals/float_interval.py
