Metadata-Version: 2.0
Name: scikit-intervals
Version: 0.1.2
Summary: handling intervals calculation in python
Home-page: https://github.com/Marcnuth/scikit-intervals
Author: Marcnuth
Author-email: marcnuth@foxmail.com
License: Apache License 2.0
Keywords: intervals,scikit,mathematics
Platform: UNKNOWN
Classifier: Development Status :: 4 - Beta
Classifier: Intended Audience :: Developers
Classifier: License :: OSI Approved :: Apache Software License
Classifier: Topic :: Scientific/Engineering :: Artificial Intelligence
Classifier: Topic :: Software Development :: Libraries
Classifier: Programming Language :: Python :: 3
Requires-Dist: arrow
Requires-Dist: numpy
